azure_tts/cli.py
azure_tts-1.0.0.dist-info/METADATA
azure_tts-1.0.0.dist-info/WHEEL
azure_tts-1.0.0.dist-info/entry_points.txt
azure_tts-1.0.0.dist-info/top_level.txt
azure_tts-1.0.0.dist-info/RECORD
