Metadata-Version: 2.1
Name: azure_tts
Version: 1.0.0
Summary: Convert text file to voice mp3 filie
Author-email: Bryt <bryt.xin.li@gmail.com>
Project-URL: Homepage, https://github.com/xin-at-marathon/pypi
Project-URL: Issues, https://github.com/xin-at-marathon/pypi/issues
Classifier: Programming Language :: Python :: 3
Classifier: License :: OSI Approved :: MIT License
Classifier: Operating System :: OS Independent
Requires-Python: >=3.6
Requires-Dist: azure-cognitiveservices-speech
